{"name":"Hugo","slug":"Hugo","count":1,"postlist":[{"title":"使用Hugo搭建个人博客","uid":"e39417a60f2c78600e5ff58d1d0519aa","slug":"使用Hugo搭建个人博客","date":"2024-11-26T00:00:00.000Z","updated":"2024-12-24T01:56:35.265Z","comments":true,"path":"api/articles/使用Hugo搭建个人博客.json","keywords":null,"cover":"https://github.com/faceman0814/picx-images-hosting/raw/master/20241114/hugo.1ovgdt2n7y.webp","text":"先来说说写这篇博客的缘由 一个程序员最好的门面是啥？除了github拥有star数高的开源项目之外当然是个人博客，无论是技术积累还是找工作，有一个属于自己的个人...","permalink":"/post/使用Hugo搭建个人博客","photos":[],"count_time":{"symbolsCount":"6.7k","symbolsTime":"6 mins."},"categories":[{"name":"DevOps","slug":"DevOps","count":11,"path":"api/categories/DevOps.json"}],"tags":[{"name":"Hugo","slug":"Hugo","count":1,"path":"api/tags/Hugo.json"}],"author":{"name":"FaceMan","slug":"blog-author","avatar":"https://github.com/faceman0814/picx-images-hosting/raw/master/20241114/image.2vermeukr5.webp","link":"/","description":"从0开始，直到1。","socials":{"github":"https://github.com/faceman0814","twitter":"","stackoverflow":"","wechat":"","qq":"","weibo":"","zhihu":"","csdn":"https://blog.csdn.net/manmanzainuli","juejin":"","customs":{"bokeyuan":{"icon":"/svg/bokeyuan.svg","link":"https://www.cnblogs.com/FaceMan"}}}}}]}